zeoliteclusterizer/__init__.py
zeoliteclusterizer/clusterizer.py
zeoliteclusterizer/extraframework.py
zeoliteclusterizer/gaussian.py
zeoliteclusterizer/scaffolds.py
zeoliteclusterizer/tests/__init__.py
zeoliteclusterizer/tests/test.py
zeoliteclusterizer-0.1.1.dist-info/DESCRIPTION.rst
zeoliteclusterizer-0.1.1.dist-info/METADATA
zeoliteclusterizer-0.1.1.dist-info/RECORD
zeoliteclusterizer-0.1.1.dist-info/WHEEL
zeoliteclusterizer-0.1.1.dist-info/metadata.json
zeoliteclusterizer-0.1.1.dist-info/top_level.txt
