Metadata-Version: 2.0
Name: zeoliteclusterizer
Version: 0.1.1
Summary: A python module built for rapid computational screening of catalysts on rigid structures
Home-page: https://github.com/ngallup/zeoliteclusterizer
Author: Nathan Gallup
Author-email: gallup@chem.ucla.edu
License: Free for non-commercial use
Keywords: chemistry quantum mechanics zeolites mofs catalysis gaussian
Platform: UNKNOWN
Classifier: Development Status :: 3 - Alpha
Classifier: Intended Audience :: Developers
Classifier: Intended Audience :: Science/Research
Classifier: Topic :: Scientific/Engineering
Classifier: Topic :: Scientific/Engineering :: Chemistry
Classifier: License :: Free for non-commercial use
Classifier: Programming Language :: Python :: 2
Classifier: Programming Language :: Python :: 3
